Week2/SimpleCircuit3Folder/simplecircuit3.v
module andgate(a,b,y);
    input a,b;
    output y;
    assign y = a & b;
endmodule
module notgate (a,y);
    input a;
    output y;
    assign y = !a;
endmodule
module orgate (a,b,y);
    input a,b;
    output y;
    assign y = a | b;
endmodule
module simple_circuit3(A,B,C,D,E,F,);
    output D,E,F;
    input A,B,C;
    wire w1; // tells that w1 and w2 is an output
    andgate G1(A,B,D);
    andgate G2(B,C,w1); // A and B are input while w1 is the output
    orgate G3(w1,A,E); // w1 and E are input while D is output
    orgate G4(E,D,F);
endmodule

Week2/SimpleCircuit3Folder/simplecircuittb3.v
module tb_simple_circuit3;
    wire D,E,F;
    reg A,B,C;
    simple_circuit3 M1(A,B,C,D,E,F,);
    initial 
    begin
        #20 A=1'b0;B=1'b0;C=1'b0;
        #20 A=1'b0;B=1'b0;C=1'b1;
        #20 A=1'b0;B=1'b1;C=1'b0;
        #20 A=1'b0;B=1'b1;C=1'b1;
        #20 A=1'b1;B=1'b0;C=1'b0;
        #20 A=1'b1;B=1'b0;C=1'b1;
        #20 A=1'b1;B=1'b1;C=1'b0;
        #20 A=1'b1;B=1'b1;C=1'b1;
    end
    initial
    begin
        $monitor($time, "a=%b, b=%b, c=%b, d=%b, e=%b, f=%b", A,B,C,D,E,F);
    end
    initial begin
        $dumpfile("simple3.vcd");
        $dumpvars(0,tb_simple_circuit3); 
    end
endmodule

Week2/SimpleCircuit3Folder/simple3.vcd
$date
	Mon Aug 11 15:08:50 2025
$end
$version
	Icarus Verilog
$end
$timescale
	1s
$end
$scope module tb_simple_circuit3 $end
$var wire 1 ! F $end
$var wire 1 " E $end
$var wire 1 # D $end
$var reg 1 $ A $end
$var reg 1 % B $end
$var reg 1 & C $end
$scope module M1 $end
$var wire 1 $ A $end
$var wire 1 % B $end
$var wire 1 & C $end
$var wire 1 ' w1 $end
$var wire 1 ! F $end
$var wire 1 " E $end
$var wire 1 # D $end
$scope module G1 $end
$var wire 1 $ a $end
$var wire 1 % b $end
$var wire 1 # y $end
$upscope $end
$scope module G2 $end
$var wire 1 % a $end
$var wire 1 & b $end
$var wire 1 ' y $end
$upscope $end
$scope module G3 $end
$var wire 1 ' a $end
$var wire 1 $ b $end
$var wire 1 " y $end
$upscope $end
$scope module G4 $end
$var wire 1 " a $end
$var wire 1 # b $end
$var wire 1 ! y $end
$upscope $end
$upscope $end
$upscope $end
$enddefinitions $end
$comment Show the parameter values. $end
$dumpall
$end
#0
$dumpvars
x'
x&
x%
x$
x#
x"
x!
$end
#20
0!
0"
0'
0#
0&
0%
0$
#40
1&
#60
0&
1%
#80
1!
1"
1'
1&
#100
0'
0&
0%
1$
#120
1&
#140
1#
0&
1%
#160
1'
1&
