Week2/SimpleCircuit1Folder/simplecircuit1.v
module andgate(a,b,y);
    input a,b;
    output y;
    assign y = a & b;
endmodule
module notgate (a,y);
    input a;
    output y;
    assign y = !a;
endmodule
module orgate (a,b,y);
    input a,b;
    output y;
    assign y = a | b;
endmodule
module simple_circuit1(A,B,C,D,E,);
    output D,E;
    input A,B,C;
    wire w1; // tells that w1 is an output
    andgate G1(A,B,w1); // A and B are input while w1 is the output
    notgate G2(C,E); // C is input while E is output
    orgate G3(w1,E,D); // w1 and E are input while D is output
endmodule

Week2/SimpleCircuit1Folder/simplecircuittb1.v
module tb_simple_circuit;
    wire D,E;
    reg A,B,C;
    simple_circuit1 M1(A,B,C,D,E,);
    initial 
    begin
        #20 A=1'b0;B=1'b0;C=1'b0;
        #20 A=1'b0;B=1'b0;C=1'b1;
        #20 A=1'b0;B=1'b1;C=1'b0;
        #20 A=1'b0;B=1'b1;C=1'b1;
        #20 A=1'b1;B=1'b0;C=1'b0;
        #20 A=1'b1;B=1'b0;C=1'b1;
        #20 A=1'b1;B=1'b1;C=1'b0;
        #20 A=1'b1;B=1'b1;C=1'b1;
    end
    initial
    begin
        $monitor($time, "a=%b, b=%b, c=%b, d=%b, e=%b", A,B,C,D,E);
    end
    initial begin
        $dumpfile("simple1.vcd");
        $dumpvars(0,tb_simple_circuit); 
    end
endmodule

Week2/SimpleCircuit1Folder/simple1.vcd
$date
	Mon Aug 11 14:39:26 2025
$end
$version
	Icarus Verilog
$end
$timescale
	1s
$end
$scope module tb_simple_circuit $end
$var wire 1 ! E $end
$var wire 1 " D $end
$var reg 1 # A $end
$var reg 1 $ B $end
$var reg 1 % C $end
$scope module M1 $end
$var wire 1 # A $end
$var wire 1 $ B $end
$var wire 1 % C $end
$var wire 1 & w1 $end
$var wire 1 ! E $end
$var wire 1 " D $end
$scope module G1 $end
$var wire 1 # a $end
$var wire 1 $ b $end
$var wire 1 & y $end
$upscope $end
$scope module G2 $end
$var wire 1 % a $end
$var wire 1 ! y $end
$upscope $end
$scope module G3 $end
$var wire 1 & a $end
$var wire 1 ! b $end
$var wire 1 " y $end
$upscope $end
$upscope $end
$upscope $end
$enddefinitions $end
$comment Show the parameter values. $end
$dumpall
$end
#0
$dumpvars
x&
x%
x$
x#
x"
x!
$end
#20
1"
0&
1!
0%
0$
0#
#40
0"
0!
1%
#60
1"
1!
0%
1$
#80
0"
0!
1%
#100
1"
1!
0%
0$
1#
#120
0"
0!
1%
#140
1"
1&
1!
0%
1$
#160
0!
1%
