Week3/FullAdderFolder/fulladder.v
module fulladd(a, b, c, sum, carry);
    input a, b, c;
    wire w1, w2, w3, w4, w5;
    output sum, carry;
    xor x0(w1, a, b);
    xor x1(sum, w1, c);
    and a0(w2, a, b);
    and a1(w3, a, c);
    and a2(w4, c, b);
    or o0(w5, w2, w3);
    or o1(carry, w5,w4);
endmodule

Week3/FullAdderFolder/fulladdertb.v
module fulladdtb;
    reg aa,bb, cc;
    wire ss,cy;
    fulladd add1(.a(aa), .b(bb), .c(cc),  .sum(ss), .carry(cy));
    initial
        begin
            $dumpfile("fulladdtest.vcd");
            $dumpvars(0, fulladdtb);
        end
    initial
        begin 
            $monitor($time, " a=%b, b=%b, c=%b,sum=%b, carry=%b", aa, bb, cc, ss, cy);
              aa = 1'b0;bb = 1'b0;cc = 1'b0;
            #5  aa = 1'b0;bb = 1'b0;cc = 1'b1;
            #5  aa = 1'b0;bb = 1'b1;cc = 1'b0;
            #5  aa = 1'b0;bb = 1'b1;cc = 1'b1;
            #5  aa = 1'b1;bb = 1'b0;cc = 1'b0;
            #5  aa = 1'b1;bb = 1'b0;cc = 1'b1;
            #5  aa = 1'b1;bb = 1'b1;cc = 1'b0;
            #5  aa = 1'b1;bb = 1'b1;cc = 1'b1;
        end
endmodule

Week3/FullAdderFolder/fulladdtest.vcd
$date
	Mon Aug 18 14:46:04 2025
$end
$version
	Icarus Verilog
$end
$timescale
	1s
$end
$scope module fulladdtb $end
$var wire 1 ! ss $end
$var wire 1 " cy $end
$var reg 1 # aa $end
$var reg 1 $ bb $end
$var reg 1 % cc $end
$scope module add1 $end
$var wire 1 # a $end
$var wire 1 $ b $end
$var wire 1 % c $end
$var wire 1 " carry $end
$var wire 1 ! sum $end
$var wire 1 & w1 $end
$var wire 1 ' w2 $end
$var wire 1 ( w3 $end
$var wire 1 ) w4 $end
$var wire 1 * w5 $end
$upscope $end
$upscope $end
$enddefinitions $end
$comment Show the parameter values. $end
$dumpall
$end
#0
$dumpvars
0*
0)
0(
0'
0&
0%
0$
0#
0"
0!
$end
#5
1!
1%
#10
1&
0%
1$
#15
1"
0!
1)
1%
#20
0"
1!
0)
0%
0$
1#
#25
1"
1*
0!
1(
1%
#30
0(
0&
1'
0%
1$
#35
1!
1(
1)
1%
