Week6/SynDownCounterJKFolder/syndocounjk.v
module jkff (input wire clk,  input wire reset,input wire j, input wire k,output reg q );
    always @(posedge clk or posedge reset) 
    begin       
    if (reset)            q <= 1'b0;                // Reset to 0       
    else begin case ({j, k})             
        2'b00: q <= q;        // No change       
        2'b01: q <= 1'b0;     // Reset       
        2'b10: q <= 1'b1;     // Set            
        2'b11: q <= ~q;       // Toggle          
    endcase       
    end 
    end
endmodule

// 2-bit synchronous down counter using JK flip-flops
module down_counter_2bit (input clk,    input reset,    output [1:0] q); 
    // JK inputs       
    wire j0, k0, j1, k1;  
    assign j0 = 1'b1;        
    assign k0 = 1'b1; 
    assign j1 = ~q[0];
    assign k1 = ~q[0];
    // Instantiate flip-flops   
    jkff jkff0 (.clk(clk), .reset(reset), .j(j0), .k(k0), .q(q[0]));  
    jkff jkff1 (.clk(clk), .reset(reset), .j(j1), .k(k1), .q(q[1]));
endmodule

Week6/SynDownCounterJKFolder/syndocounjktb.v
module tb_down_counter_2bit;   
    reg clk, reset;    
    wire [1:0] q;   
 // Instantiate counter  
    down_counter_2bit uut (.clk(clk), .reset(reset), .q(q));    
// Clock generation
initial begin    
    clk = 0;     
    forever #5 clk = ~clk;   // Clock period = 10   
end
initial begin
    $dumpfile("down_counter_jk.vcd");        
    $dumpvars(0, tb_down_counter_2bit);
end        
initial begin
    $display("Time\tClk\tReset\tQ1 Q0");       
    $monitor("%0t\t%b\t%b\t%b %b", $time, clk, reset, q[1], q[0]);   
    reset = 1; #10;   // Apply reset     
    reset = 0;        #80;              // Run counter for a while        
    reset = 1; #10;   // Reset again  
    reset = 0;        #40;      
    $finish; 
end
endmodule

Week6/SynDownCounterJKFolder/down_counter_jk.vcd
$date
	Mon Sep 29 14:46:59 2025
$end
$version
	Icarus Verilog
$end
$timescale
	1s
$end
$scope module tb_down_counter_2bit $end
$var wire 2 ! q [1:0] $end
$var reg 1 " clk $end
$var reg 1 # reset $end
$scope module uut $end
$var wire 1 " clk $end
$var wire 1 $ j0 $end
$var wire 1 % j1 $end
$var wire 1 & k0 $end
$var wire 1 ' k1 $end
$var wire 1 # reset $end
$var wire 2 ( q [1:0] $end
$scope module jkff0 $end
$var wire 1 " clk $end
$var wire 1 $ j $end
$var wire 1 & k $end
$var wire 1 # reset $end
$var reg 1 ) q $end
$upscope $end
$scope module jkff1 $end
$var wire 1 " clk $end
$var wire 1 % j $end
$var wire 1 ' k $end
$var wire 1 # reset $end
$var reg 1 * q $end
$upscope $end
$upscope $end
$upscope $end
$enddefinitions $end
$comment Show the parameter values. $end
$dumpall
$end
#0
$dumpvars
0*
0)
b0 (
1'
1&
1%
1$
1#
0"
b0 !
$end
#5
1"
#10
0"
0#
#15
0'
0%
1)
b11 !
b11 (
1*
1"
#20
0"
#25
1'
1%
b10 !
b10 (
0)
1"
#30
0"
#35
0'
0%
1)
b1 !
b1 (
0*
1"
#40
0"
#45
1'
1%
b0 !
b0 (
0)
1"
#50
0"
#55
0'
0%
1)
b11 !
b11 (
1*
1"
#60
0"
#65
1'
1%
b10 !
b10 (
0)
1"
#70
0"
#75
0'
0%
1)
b1 !
b1 (
0*
1"
#80
0"
#85
1'
1%
b0 !
b0 (
0)
1"
#90
0"
1#
#95
1"
#100
0"
0#
#105
0'
0%
1)
b11 !
b11 (
1*
1"
#110
0"
#115
1'
1%
b10 !
b10 (
0)
1"
#120
0"
#125
0'
0%
1)
b1 !
b1 (
0*
1"
#130
0"
#135
1'
1%
b0 !
b0 (
0)
1"
