Week6/RingCounterDFolder/ringd.v
`timescale 1ns/1ps
module ring_counter (
    input  wire clk,
    input  wire rst,       // async reset, active high
    output reg  [2:0] q
);
    always @(posedge clk or posedge rst) begin
        if (rst)
            q <= 3'b001;              // seed the ring with "001"
        else
            q <= {q[1:0], q[2]};      // rotate left
    end
endmodule

Week6/RingCounterDFolder/ringdtb.v
`timescale 1ns/1ps
module tb_ring_counter;
    reg clk, rst;
    wire [2:0] q;

    // Instantiate DUT
    ring_counter uut (.clk(clk), .rst(rst), .q(q));

    // Clock generation: 10ns period
    always #5 clk = ~clk;

    initial begin
        $display("Time\tCLK\tRST\tQ2 Q1 Q0");
    end

    // Print on every rising edge
    always @(posedge clk) begin
        $display("%0t\t%b\t%b\t%b %b %b", $time, clk, rst, q[2], q[1], q[0]);
    end

    initial begin
        $dumpfile("ring_counter.vcd");
        $dumpvars(0, tb_ring_counter);

        clk = 0;
        rst = 1;   // Apply reset
        #10;
        rst = 0;   // Release reset

        #100;
        $finish;
    end
endmodule

Week6/RingCounterDFolder/ring_counter.vcd
$date
	Mon Sep 29 17:44:59 2025
$end
$version
	Icarus Verilog
$end
$timescale
	1ps
$end
$scope module tb_ring_counter $end
$var wire 3 ! q [2:0] $end
$var reg 1 " clk $end
$var reg 1 # rst $end
$scope module uut $end
$var wire 1 " clk $end
$var wire 1 # rst $end
$var reg 3 $ q [2:0] $end
$upscope $end
$upscope $end
$enddefinitions $end
$comment Show the parameter values. $end
$dumpall
$end
#0
$dumpvars
b1 $
1#
0"
b1 !
$end
#5000
1"
#10000
0"
0#
#15000
b10 !
b10 $
1"
#20000
0"
#25000
b100 !
b100 $
1"
#30000
0"
#35000
b1 !
b1 $
1"
#40000
0"
#45000
b10 !
b10 $
1"
#50000
0"
#55000
b100 !
b100 $
1"
#60000
0"
#65000
b1 !
b1 $
1"
#70000
0"
#75000
b10 !
b10 $
1"
#80000
0"
#85000
b100 !
b100 $
1"
#90000
0"
#95000
b1 !
b1 $
1"
#100000
0"
#105000
b10 !
b10 $
1"
