Week2/SimpleCircuit4Folder/simplecircuit4.v
module andgate(a,b,y);
    input a,b;
    output y;
    assign y = a & b;
endmodule
module notgate (a,y);
    input a;
    output y;
    assign y = !a;
endmodule
module orgate (a,b,y);
    input a,b;
    output y;
    assign y = a | b;
endmodule
module simple_circuit4(T,P,O,D,F,);
    output D,F;
    input T,P,O;
    andgate G1(T,P,D); // A and B are input while w1 is the output
    orgate G3(D,O,F); // w1 and E are input while D is output
endmodule

Week2/SimpleCircuit4Folder/simplecircuittb4.v
module tb_simple_circuit4;
    wire D,F;
    reg T,P,O;
    simple_circuit4 M1(T,P,O,D,F,);
    initial 
    begin
        #20 T=1'b0;P=1'b0;O=1'b0;
        #20 T=1'b0;P=1'b0;O=1'b1;
        #20 T=1'b0;P=1'b1;O=1'b0;
        #20 T=1'b0;P=1'b1;O=1'b1;
        #20 T=1'b1;P=1'b0;O=1'b0;
        #20 T=1'b1;P=1'b0;O=1'b1;
        #20 T=1'b1;P=1'b1;O=1'b0;
        #20 T=1'b1;P=1'b1;O=1'b1;
    end
    initial
    begin
        $monitor($time, "t=%b, p=%b, o=%b, d=%b, f=%b", T,P,O,D,F);
    end
    initial begin
        $dumpfile("simple4.vcd");
        $dumpvars(0,tb_simple_circuit4); 
    end
endmodule

Week2/SimpleCircuit4Folder/simple4.vcd
$date
	Mon Aug 11 15:21:17 2025
$end
$version
	Icarus Verilog
$end
$timescale
	1s
$end
$scope module tb_simple_circuit4 $end
$var wire 1 ! F $end
$var wire 1 " D $end
$var reg 1 # O $end
$var reg 1 $ P $end
$var reg 1 % T $end
$scope module M1 $end
$var wire 1 # O $end
$var wire 1 $ P $end
$var wire 1 % T $end
$var wire 1 ! F $end
$var wire 1 " D $end
$scope module G1 $end
$var wire 1 % a $end
$var wire 1 $ b $end
$var wire 1 " y $end
$upscope $end
$scope module G3 $end
$var wire 1 " a $end
$var wire 1 # b $end
$var wire 1 ! y $end
$upscope $end
$upscope $end
$upscope $end
$enddefinitions $end
$comment Show the parameter values. $end
$dumpall
$end
#0
$dumpvars
x%
x$
x#
x"
x!
$end
#20
0!
0"
0#
0$
0%
#40
1!
1#
#60
0!
0#
1$
#80
1!
1#
#100
0!
0#
0$
1%
#120
1!
1#
#140
1"
0#
1$
#160
1#
