Week6/JohnsonCounterDFolder/johncounter.v
`timescale 1ns/1ps
module johnson_counter (
    input  wire clk,
    input  wire rst,       // async reset, active high
    output reg  [2:0] q
);
    always @(posedge clk or posedge rst) begin
        if (rst)
            q <= 3'b000;                  // Johnson starts at all zeros
        else
            q <= {q[1:0], ~q[2]};         // shift left, insert inverted MSB
    end
endmodule

Week6/JohnsonCounterDFolder/johncountertb.v
`timescale 1ns/1ps
module tb_johnson_counter;
    reg clk, rst;
    wire [2:0] q;

    // Instantiate DUT
    johnson_counter uut (.clk(clk), .rst(rst), .q(q));

    // Clock generation: 10ns period
    always #5 clk = ~clk;

    initial begin
        $display("Time\tCLK\tRST\tQ2 Q1 Q0");
    end

    // Print on every rising edge
    always @(posedge clk) begin
        $display("%0t\t%b\t%b\t%b %b %b", $time, clk, rst, q[2], q[1], q[0]);
    end

    initial begin
        $dumpfile("johnson_counter.vcd");
        $dumpvars(0, tb_johnson_counter);

        clk = 0;
        rst = 1;   // Apply reset
        #10;
        rst = 0;   // Release reset

        #120;
        $finish;
    end
endmodule

Week6/JohnsonCounterDFolder/johnson_counter.vcd
$date
	Mon Sep 29 17:55:48 2025
$end
$version
	Icarus Verilog
$end
$timescale
	1ps
$end
$scope module tb_johnson_counter $end
$var wire 3 ! q [2:0] $end
$var reg 1 " clk $end
$var reg 1 # rst $end
$scope module uut $end
$var wire 1 " clk $end
$var wire 1 # rst $end
$var reg 3 $ q [2:0] $end
$upscope $end
$upscope $end
$enddefinitions $end
$comment Show the parameter values. $end
$dumpall
$end
#0
$dumpvars
b0 $
1#
0"
b0 !
$end
#5000
1"
#10000
0"
0#
#15000
b1 !
b1 $
1"
#20000
0"
#25000
b11 !
b11 $
1"
#30000
0"
#35000
b111 !
b111 $
1"
#40000
0"
#45000
b110 !
b110 $
1"
#50000
0"
#55000
b100 !
b100 $
1"
#60000
0"
#65000
b0 !
b0 $
1"
#70000
0"
#75000
b1 !
b1 $
1"
#80000
0"
#85000
b11 !
b11 $
1"
#90000
0"
#95000
b111 !
b111 $
1"
#100000
0"
#105000
b110 !
b110 $
1"
#110000
0"
#115000
b100 !
b100 $
1"
#120000
0"
#125000
b0 !
b0 $
1"
