Week6/SynUpDownCounterJKFolder/synupdocounjk.v
module jkff (input wire clk,  input wire rst,input wire j, input wire k,output reg q );
    always @(posedge clk or posedge rst) 
    begin       
    if (rst)            q <= 1'b0;                // Reset to 0       
    else begin case ({j, k})             
        2'b00: q <= q;        // No change       
        2'b01: q <= 1'b0;     // Reset       
        2'b10: q <= 1'b1;     // Set            
        2'b11: q <= ~q;       // Toggle          
    endcase       
    end 
    end
endmodule


module updown_counter_2bit (input  wire clk,input  wire rst,input  wire up_down,output wire [1:0] q);  
    wire j0, k0, j1, k1;  
    assign j0 = 1'b1;        
    assign k0 = 1'b1; 
    assign j1 = up_down * q[0] + ~up_down * q[0];
    assign k1 = up_down * q[0] + ~up_down * q[0];
    jkff jkff0 (.clk(clk), .rst(rst), .j(j0), .k(k0), .q(q[0]));  
    jkff jkff1 (.clk(clk), .rst(rst), .j(j1), .k(k1), .q(q[1]));
endmodule

Week6/SynUpDownCounterJKFolder/synupdocounjktb.v
`timescale 1ns/1ps
module tb_updown_counter_2bit; 
reg clk = 0; 
reg rst = 1;
reg up_down = 1;  
wire [1:0] q; 
updown_counter_2bit dut (.clk(clk), .rst(rst), .up_down(up_down), .q(q));  
// 10 ns period clock  
always #5 clk = ~clk;
// Print after each synchronous update
always @(posedge clk) begin
  $display("%0t  clk=%0b rst=%0b upDn=%0b  Q=%0b %0b",$time, clk, rst, up_down, q[1], q[0]);
end
initial begin
  $monitor("%0t\t%b\t%b\t%b\t%b %b", $time, clk, rst, up_down, q[1], q[0]);
end

initial begin
  $dumpfile("updown_2bit_jk.vcd");
  $dumpvars(0, tb_updown_counter_2bit);
  // Keep reset high for one edge -> Q becomes 00 at first posedge
  @(negedge clk); rst = 1;
  @(negedge clk); rst = 0;        // release just before a posedge

  // Count UP to reach 11: 00 -> 01 -> 10 -> 11
  up_down = 1;
  repeat (3) @(negedge clk);      // change only on negedge

  // Now count DOWN: 11 -> 10 -> 01 -> 00
  up_down = 0;
  repeat (3) @(negedge clk);
  $finish;
end
endmodule

Week6/SynUpDownCounterJKFolder/updown_2bit_jk.vcd
$date
	Mon Sep 29 15:18:52 2025
$end
$version
	Icarus Verilog
$end
$timescale
	1ps
$end
$scope module tb_updown_counter_2bit $end
$var wire 2 ! q [1:0] $end
$var reg 1 " clk $end
$var reg 1 # rst $end
$var reg 1 $ up_down $end
$scope module dut $end
$var wire 1 " clk $end
$var wire 1 % j0 $end
$var wire 1 & k0 $end
$var wire 1 # rst $end
$var wire 1 $ up_down $end
$var wire 2 ' q [1:0] $end
$var wire 1 ( k1 $end
$var wire 1 ) j1 $end
$scope module jkff0 $end
$var wire 1 " clk $end
$var wire 1 % j $end
$var wire 1 & k $end
$var wire 1 # rst $end
$var reg 1 * q $end
$upscope $end
$scope module jkff1 $end
$var wire 1 " clk $end
$var wire 1 ) j $end
$var wire 1 ( k $end
$var wire 1 # rst $end
$var reg 1 + q $end
$upscope $end
$upscope $end
$upscope $end
$enddefinitions $end
$comment Show the parameter values. $end
$dumpall
$end
#0
$dumpvars
0+
0*
0)
0(
b0 '
1&
1%
1$
1#
0"
b0 !
$end
#5000
1"
#10000
0"
#15000
1"
#20000
0#
0"
#25000
1(
1)
b1 !
b1 '
1*
1"
#30000
0"
#35000
0(
0)
0*
b10 !
b10 '
1+
1"
#40000
0"
#45000
1(
1)
b11 !
b11 '
1*
1"
#50000
1)
1(
0$
0"
#55000
0(
0)
0*
b0 !
b0 '
0+
1"
#60000
0"
#65000
1(
1)
b1 !
b1 '
1*
1"
#70000
0"
#75000
0(
0)
0*
b10 !
b10 '
1+
1"
