Week4/4-1MuxFolder/4-1mux.v
module mux2 (input wire i0, i1, j, output wire o);
    assign o = j==0?i0:i1;
endmodule

module mux4 (input wire [0:3] i, input wire j1, j0, output wire o);  
wire  t0, t1;  
mux2 mux2_0 (i[0],i[1],j0,t0);  
mux2 mux2_1 (i[2],i[3],j0,t1);  
mux2 mux2_2 (t0,t1,j1,o);
endmodule

Week4/2-1MuxFolder/2-1muxtb.v
module TB;
reg A,B,S;
wire X;
initial
    begin
        $dumpfile("2-1mux.vcd");
        $dumpvars(0,TB);
    end
mux2 newMUX(.i0(A), .i1(B), .j(S), .o(X));
initial
    begin
        $monitor($time, " S=%b, A=%b, B=%b, Output=%b", S, A, B, X);
        S = 1'b0;    A = 1'b0;B = 1'b0;
        #5 S = 1'b0;A = 1'b0;B = 1'b1;
        #5 S = 1'b0;A = 1'b1;B = 1'b0;
        #5 S = 1'b0;A = 1'b1;B = 1'b1;
        #5 S = 1'b1;A = 1'b0;B = 1'b0;
        #5 S = 1'b1;A = 1'b0;B = 1'b1;
        #5 S = 1'b1;A = 1'b1;B = 1'b0;
        #5 S=1'b1;A = 1'b1;B = 1'b1;
    end
endmodule

Week4/2-1MuxFolder/2-1mux.vcd
$date
	Mon Aug 25 14:25:04 2025
$end
$version
	Icarus Verilog
$end
$timescale
	1s
$end
$scope module TB $end
$var wire 1 ! X $end
$var reg 1 " A $end
$var reg 1 # B $end
$var reg 1 $ S $end
$scope module newMUX $end
$var wire 1 " i0 $end
$var wire 1 # i1 $end
$var wire 1 $ j $end
$var wire 1 ! o $end
$upscope $end
$upscope $end
$enddefinitions $end
$comment Show the parameter values. $end
$dumpall
$end
#0
$dumpvars
0$
0#
0"
0!
$end
#5
1#
#10
1!
0#
1"
#15
1#
#20
0!
0#
0"
1$
#25
1!
1#
#30
0!
0#
1"
#35
1!
1#
